datasett/__init__.py
datasett/_nbdev.py
datasett/core.py
datasett/data.py
datasett-0.0.1.dist-info/LICENSE
datasett-0.0.1.dist-info/WHEEL
datasett-0.0.1.dist-info/METADATA
datasett-0.0.1.dist-info/RECORD
